{
  "id": 8253,
  "title": "EIP-8253: Bump nonce of zero-nonce storage accounts",
  "status": "Draft",
  "description": "Set nonce to 1 for accounts with empty code, zero nonce, and non-empty storage via an irregular state transition",
  "author": "Jochem Brouwer (@jochem-brouwer)",
  "type": "Standards Track",
  "category": "Core",
  "createdDate": "2026-05-05",
  "discussionLink": "https://ethereum-magicians.org/t/eip-8253-upgrade-pre-spurious-dragon-accounts/28505",
  "forkRelationships": [],
  "tradeoffs": null
}
